misp_feed_generator/__init__.py
misp_feed_generator/main.py
misp_feed_generator/server.py
misp_feed_generator/test_simulation.py
misp_feed_generator/utils.py
crowdsec_misp_feed_generator-0.0.1.dist-info/LICENSE
crowdsec_misp_feed_generator-0.0.1.dist-info/METADATA
crowdsec_misp_feed_generator-0.0.1.dist-info/WHEEL
crowdsec_misp_feed_generator-0.0.1.dist-info/entry_points.txt
crowdsec_misp_feed_generator-0.0.1.dist-info/top_level.txt
crowdsec_misp_feed_generator-0.0.1.dist-info/RECORD
