Metadata-Version: 2.1
Name: crowdsec-misp-feed-generator
Version: 0.0.1
Summary: CrowdSec MISP Feed Generator
Home-page: https://github.com/crowdsecurity/crowdsec-misp-feed-generator
Author: CrowdSec
Author-email: core.tech@crowdsec.net
Project-URL: Bug Tracker, https://github.com/crowdsecurity/crowdsec-misp-feed-generator/issues
Classifier: Programming Language :: Python :: 3
Classifier: License :: OSI Approved :: MIT License
Classifier: Operating System :: OS Independent
Requires-Python: >=3.6
License-File: LICENSE
Requires-Dist: pyyaml
Requires-Dist: requests
Requires-Dist: pytimeparse
